app/__init__.py
app/main.py
app/models.py
app/crud/__init__.py
app/crud/additions.py
app/crud/assay_data.py
app/crud/batches.py
app/crud/compounds.py
app/crud/properties.py
app/crud/validators.py
app/services/properties/complex_validator.py
app/services/properties/numeric_constraint.py
app/services/properties/property_service.py
app/services/properties/property_validator.py
app/services/registrars/assay_result_registrar.py
app/services/registrars/assay_run_registrar.py
app/services/registrars/base_registrar.py
app/services/registrars/batch_registrar.py
app/services/registrars/compound_registrar.py
app/services/registrars/writer.py
app/services/search/engine.py
app/services/search/field_resolver.py
app/services/search/operators.py
app/services/search/parser.py
app/services/search/query_builder.py
app/services/search/search_filter_builder.py
app/services/search/utils/aggregation_operators.py
app/services/search/utils/helper_functions.py
app/services/search/utils/join_tools.py
app/setup/database.py
app/utils/admin_utils.py
app/utils/chemistry_utils.py
app/utils/enums.py
app/utils/logging_utils.py
app/utils/registrar_utils.py
app/utils/sql_utils.py
app/utils/type_casting_utils.py
dg_mol_track-0.6.19.dist-info/licenses/LICENSE
dg_mol_track-0.6.19.dist-info/METADATA
dg_mol_track-0.6.19.dist-info/WHEEL
dg_mol_track-0.6.19.dist-info/entry_points.txt
dg_mol_track-0.6.19.dist-info/top_level.txt
dg_mol_track-0.6.19.dist-info/RECORD
