Metadata-Version: 2.4
Name: dg-mol-track
Version: 0.6.19
Author-email: Oleksandra Serhiienko <oserhiienko@datagrok.ai>
License: MIT License
Requires-Python: >=3.11
License-File: LICENSE
Requires-Dist: fastapi>=0.115.12
Requires-Dist: httpx>=0.28.1
Requires-Dist: orjson>=3.11.1
Requires-Dist: pandas>=2.3.0
Requires-Dist: psycopg2-binary>=2.9.10
Requires-Dist: pydantic==2.10.6
Requires-Dist: pytest>=8.3.5
Requires-Dist: pytest-asyncio>=0.26.0
Requires-Dist: python-dateutil>=2.9.0.post0
Requires-Dist: python-dotenv>=1.1.0
Requires-Dist: python-multipart>=0.0.20
Requires-Dist: pyyaml==6.0.2
Requires-Dist: rdkit>=2025.3.1
Requires-Dist: sqlalchemy>=2.0.40
Requires-Dist: sqlmodel>=0.0.24
Requires-Dist: uvicorn>=0.34.2
Requires-Dist: pyarrow>=16.1.0
Requires-Dist: common-expression-language
Requires-Dist: typer>=0.16.0
Requires-Dist: requests>=2.32.4
Requires-Dist: pydantic-settings
Dynamic: license-file
